model_explorer/__init__.py
model_explorer/__main__.py
model_explorer/adapter.py
model_explorer/adapter_runner.py
model_explorer/apis.py
model_explorer/builtin_graphdef_adapter.py
model_explorer/builtin_mlir_adapter.py
model_explorer/builtin_pytorch_exportedprogram_adapter.py
model_explorer/builtin_tf_direct_adapter.py
model_explorer/builtin_tf_mlir_adapter.py
model_explorer/builtin_tflite_flatbuffer_adapter.py
model_explorer/builtin_tflite_mlir_adapter.py
model_explorer/cmdline.py
model_explorer/config.py
model_explorer/config_editor.py
model_explorer/consts.py
model_explorer/extension_base.py
model_explorer/extension_class_processor.py
model_explorer/extension_manager.py
model_explorer/extension_matadata.py
model_explorer/file_change_handler.py
model_explorer/graph_builder.py
model_explorer/ndp_runner.py
model_explorer/node_data_builder.py
model_explorer/node_data_provider.py
model_explorer/pytorch_exported_program_adater_impl.py
model_explorer/registered_extension.py
model_explorer/server.py
model_explorer/server_directive_dispatcher.py
model_explorer/server_director.py
model_explorer/singleton.py
model_explorer/types.py
model_explorer/utils.py
model_explorer/web_app/index.html
model_explorer/web_app/main-RJNGEZX2.js
model_explorer/web_app/polyfills-B6TNHZQ6.js
model_explorer/web_app/styles-IRUOMJAV.css
model_explorer/web_app/worker-L3PYLAD3.js
model_explorer/web_app/static_files/5aUo9-KzpRiLCAt4Unrc-xIKmCU5qE9Gh09GixI.woff2
model_explorer/web_app/static_files/5aUo9-KzpRiLCAt4Unrc-xIKmCU5qE9Ghk9GixI.woff2
model_explorer/web_app/static_files/5aUo9-KzpRiLCAt4Unrc-xIKmCU5qE9GiU9G.woff2
model_explorer/web_app/static_files/5aUo9-KzpRiLCAt4Unrc-xIKmCU5qE9Gik9GixI.woff2
model_explorer/web_app/static_files/5aUo9-KzpRiLCAt4Unrc-xIKmCU5qE9GjU9GixI.woff2
model_explorer/web_app/static_files/5aUp9-KzpRiLCAt4Unrc-xIKmCU5oLlVnmZjtiu7.woff2
model_explorer/web_app/static_files/5aUp9-KzpRiLCAt4Unrc-xIKmCU5oLlVnmdjtiu7.woff2
ai_edge_model_explorer-0.1.30.dist-info/METADATA
ai_edge_model_explorer-0.1.30.dist-info/WHEEL
ai_edge_model_explorer-0.1.30.dist-info/entry_points.txt
ai_edge_model_explorer-0.1.30.dist-info/top_level.txt
ai_edge_model_explorer-0.1.30.dist-info/RECORD
