Metadata-Version: 2.4
Name: ai-edge-model-explorer
Version: 0.1.30
Summary: A modern model graph visualizer and debugger
Author-email: Google LLC <opensource@google.com>
Classifier: Programming Language :: Python :: 3.9
Classifier: Programming Language :: Python :: 3.10
Classifier: Programming Language :: Python :: 3.11
Classifier: Programming Language :: Python :: 3.12
Classifier: Programming Language :: Python :: 3.13
Classifier: License :: OSI Approved :: Apache Software License
Requires-Python: >=3.9
Requires-Dist: flask
Requires-Dist: ipython
Requires-Dist: ai-edge-model-explorer-adapter~=0.1.14; sys_platform != "win32"
Requires-Dist: dacite
Requires-Dist: packaging
Requires-Dist: portpicker
Requires-Dist: requests
Requires-Dist: termcolor
Requires-Dist: typing-extensions
Requires-Dist: numpy
Requires-Dist: watchdog
